{
  "id": "add-seed",
  "command": "add:seed",
  "description": "Generate a database seed file that inserts test records into a Drizzle table",
  "token_estimate": 20,
  "output_paths": [
    "db/seed/{{name}}.ts"
  ],
  "next_steps": [
    "Run `npx tsx db/seed/{{name}}.ts` to seed your database",
    "Add it to your `package.json` scripts: `\"seed:{{name}}\": \"tsx db/seed/{{name}}.ts\"`"
  ],
  "schema": {
    "type": "object",
    "required": ["name"],
    "properties": {
      "name": {
        "type": "string",
        "description": "Table/entity name that matches the schema file (e.g. 'users', 'products')"
      },
      "count": {
        "type": "number",
        "default": 10,
        "description": "Number of seed records to generate"
      }
    }
  }
}
